deep_rectifiers/__init__.py
deep_rectifiers/activation_space.py
deep_rectifiers/demo_1.py
deep_rectifiers/ensembles.py
deep_rectifiers/unsupervised_pretraining.py
deep_rectifiers/utils.py
deep_rectifiers/validation.py
deep_rectifiers/variable_importance.py
deep_rectifiers/weight_norm.py
deep_rectifiers/weight_space.py
deep_rectifiers-1.0.0.dist-info/DESCRIPTION.rst
deep_rectifiers-1.0.0.dist-info/METADATA
deep_rectifiers-1.0.0.dist-info/RECORD
deep_rectifiers-1.0.0.dist-info/WHEEL
deep_rectifiers-1.0.0.dist-info/metadata.json
deep_rectifiers-1.0.0.dist-info/top_level.txt
