Metadata-Version: 2.0
Name: deep-rectifiers
Version: 1.0.0
Summary: Tools for analysing deep rectifier networks
Home-page: http://paulispace.com/projects/
Author: Aidan Rocke
Author-email: aidanrocke@gmail.com
License: MIT
Keywords: deep neural networks
Platform: UNKNOWN
Classifier: Development Status :: 3 - Alpha
Classifier: Intended Audience :: Developers
Classifier: Topic :: Software Development :: Build Tools
Classifier: License :: OSI Approved :: MIT License
Classifier: Programming Language :: Python :: 3
Classifier: Programming Language :: Python :: 3.3
Classifier: Programming Language :: Python :: 3.4
Classifier: Programming Language :: Python :: 3.5
Requires-Dist: keras (==2.0.3)
Requires-Dist: matplotlib (==2.0.0)
Requires-Dist: numpy (==1.12.1)
Requires-Dist: pandas (==0.19.2)
Requires-Dist: scipy (==0.19.0)
Requires-Dist: seaborn (==0.7.1)
Requires-Dist: sklearn (==0.18.1)
